{
  "primitive": {
    "color": {
      "blue": {
        "50":  { "value": "#EFF6FF", "type": "color" },
        "100": { "value": "#DBEAFE", "type": "color" },
        "200": { "value": "#BFDBFE", "type": "color" },
        "300": { "value": "#93C5FD", "type": "color" },
        "400": { "value": "#60A5FA", "type": "color" },
        "500": { "value": "#2563EB", "type": "color" },
        "600": { "value": "#1D4ED8", "type": "color" },
        "700": { "value": "#1E40AF", "type": "color" },
        "800": { "value": "#1E3A8A", "type": "color" },
        "900": { "value": "#172554", "type": "color" }
      },
      "gray": {
        "0":   { "value": "#FFFFFF", "type": "color" },
        "50":  { "value": "#F9FAFB", "type": "color" },
        "100": { "value": "#F3F4F6", "type": "color" },
        "200": { "value": "#E5E7EB", "type": "color" },
        "300": { "value": "#D1D5DB", "type": "color" },
        "400": { "value": "#9CA3AF", "type": "color" },
        "500": { "value": "#6B7280", "type": "color" },
        "600": { "value": "#4B5563", "type": "color" },
        "700": { "value": "#374151", "type": "color" },
        "800": { "value": "#1F2937", "type": "color" },
        "900": { "value": "#111827", "type": "color" },
        "950": { "value": "#030712", "type": "color" }
      },
      "red":    { "500": { "value": "#EF4444", "type": "color" } },
      "green":  { "500": { "value": "#22C55E", "type": "color" } },
      "yellow": { "500": { "value": "#EAB308", "type": "color" } }
    },
    "spacing": {
      "1":  { "value": "4px",  "type": "spacing" },
      "2":  { "value": "8px",  "type": "spacing" },
      "3":  { "value": "12px", "type": "spacing" },
      "4":  { "value": "16px", "type": "spacing" },
      "5":  { "value": "20px", "type": "spacing" },
      "6":  { "value": "24px", "type": "spacing" },
      "8":  { "value": "32px", "type": "spacing" },
      "10": { "value": "40px", "type": "spacing" },
      "12": { "value": "48px", "type": "spacing" },
      "16": { "value": "64px", "type": "spacing" }
    },
    "radius": {
      "sm":   { "value": "4px",    "type": "borderRadius" },
      "md":   { "value": "8px",    "type": "borderRadius" },
      "lg":   { "value": "12px",   "type": "borderRadius" },
      "xl":   { "value": "16px",   "type": "borderRadius" },
      "full": { "value": "9999px", "type": "borderRadius" }
    },
    "fontSize": {
      "11": { "value": "11px", "type": "fontSize" },
      "12": { "value": "12px", "type": "fontSize" },
      "14": { "value": "14px", "type": "fontSize" },
      "16": { "value": "16px", "type": "fontSize" },
      "18": { "value": "18px", "type": "fontSize" },
      "20": { "value": "20px", "type": "fontSize" },
      "24": { "value": "24px", "type": "fontSize" },
      "30": { "value": "30px", "type": "fontSize" },
      "36": { "value": "36px", "type": "fontSize" },
      "44": { "value": "44px", "type": "fontSize" },
      "56": { "value": "56px", "type": "fontSize" },
      "72": { "value": "72px", "type": "fontSize" }
    }
  },

  "semantic": {
    "color": {
      "bg": {
        "primary":   { "value": "{primitive.color.gray.0}",   "type": "color" },
        "secondary": { "value": "{primitive.color.gray.50}",  "type": "color" },
        "tertiary":  { "value": "{primitive.color.gray.100}", "type": "color" },
        "inverse":   { "value": "{primitive.color.gray.900}", "type": "color" }
      },
      "text": {
        "primary":   { "value": "{primitive.color.gray.900}", "type": "color" },
        "secondary": { "value": "{primitive.color.gray.500}", "type": "color" },
        "disabled":  { "value": "{primitive.color.gray.300}", "type": "color" },
        "inverse":   { "value": "{primitive.color.gray.0}",   "type": "color" }
      },
      "border": {
        "default": { "value": "{primitive.color.gray.200}", "type": "color" },
        "strong":  { "value": "{primitive.color.gray.400}", "type": "color" }
      },
      "interactive": {
        "primary": { "value": "{primitive.color.blue.500}", "type": "color" },
        "hover":   { "value": "{primitive.color.blue.600}", "type": "color" }
      },
      "error":   { "value": "{primitive.color.red.500}",    "type": "color" },
      "success": { "value": "{primitive.color.green.500}",  "type": "color" },
      "warning": { "value": "{primitive.color.yellow.500}", "type": "color" }
    },
    "space": {
      "none": { "value": "0px",                        "type": "spacing" },
      "xs":   { "value": "{primitive.spacing.1}",      "type": "spacing" },
      "sm":   { "value": "{primitive.spacing.2}",      "type": "spacing" },
      "md":   { "value": "{primitive.spacing.3}",      "type": "spacing" },
      "lg":   { "value": "{primitive.spacing.4}",      "type": "spacing" },
      "xl":   { "value": "{primitive.spacing.5}",      "type": "spacing" },
      "2xl":  { "value": "{primitive.spacing.6}",      "type": "spacing" },
      "3xl":  { "value": "{primitive.spacing.8}",      "type": "spacing" },
      "4xl":  { "value": "{primitive.spacing.10}",     "type": "spacing" },
      "5xl":  { "value": "{primitive.spacing.12}",     "type": "spacing" },
      "6xl":  { "value": "{primitive.spacing.16}",     "type": "spacing" }
    },
    "borderRadius": {
      "none": { "value": "0px",                       "type": "borderRadius" },
      "sm":   { "value": "{primitive.radius.sm}",     "type": "borderRadius" },
      "md":   { "value": "{primitive.radius.md}",     "type": "borderRadius" },
      "lg":   { "value": "{primitive.radius.lg}",     "type": "borderRadius" },
      "xl":   { "value": "{primitive.radius.xl}",     "type": "borderRadius" },
      "full": { "value": "{primitive.radius.full}",   "type": "borderRadius" }
    },
    "fontSize": {
      "display-xl": { "value": "{primitive.fontSize.72}", "type": "fontSize" },
      "display-lg": { "value": "{primitive.fontSize.56}", "type": "fontSize" },
      "display-md": { "value": "{primitive.fontSize.44}", "type": "fontSize" },
      "heading-xl": { "value": "{primitive.fontSize.36}", "type": "fontSize" },
      "heading-lg": { "value": "{primitive.fontSize.30}", "type": "fontSize" },
      "heading-md": { "value": "{primitive.fontSize.24}", "type": "fontSize" },
      "heading-sm": { "value": "{primitive.fontSize.20}", "type": "fontSize" },
      "body-lg":    { "value": "{primitive.fontSize.18}", "type": "fontSize" },
      "body-md":    { "value": "{primitive.fontSize.16}", "type": "fontSize" },
      "body-sm":    { "value": "{primitive.fontSize.14}", "type": "fontSize" },
      "label-lg":   { "value": "{primitive.fontSize.14}", "type": "fontSize" },
      "label-md":   { "value": "{primitive.fontSize.12}", "type": "fontSize" },
      "label-sm":   { "value": "{primitive.fontSize.11}", "type": "fontSize" }
    },
    "fontFamily": {
      "sans": { "value": "'Inter', sans-serif", "type": "fontFamily" }
    },
    "fontWeight": {
      "regular":  { "value": "400", "type": "fontWeight" },
      "medium":   { "value": "500", "type": "fontWeight" },
      "semibold": { "value": "600", "type": "fontWeight" },
      "bold":     { "value": "700", "type": "fontWeight" }
    },
    "lineHeight": {
      "none":    { "value": "1",     "type": "lineHeight" },
      "tight":   { "value": "1.25",  "type": "lineHeight" },
      "snug":    { "value": "1.375", "type": "lineHeight" },
      "normal":  { "value": "1.5",   "type": "lineHeight" },
      "relaxed": { "value": "1.625", "type": "lineHeight" }
    }
  },

  "component": {
    "button": {
      "bg": {
        "default":  { "value": "{semantic.color.interactive.primary}", "type": "color" },
        "hover":    { "value": "{semantic.color.interactive.hover}",   "type": "color" },
        "active":   { "value": "{primitive.color.blue.700}",           "type": "color" },
        "selected": { "value": "{primitive.color.blue.700}",           "type": "color" },
        "disabled": { "value": "{primitive.color.gray.200}",           "type": "color" },
        "error":    { "value": "{semantic.color.error}",               "type": "color" }
      },
      "skeleton-bg":  { "value": "{primitive.color.gray.200}",         "type": "color" },
      "text":         { "value": "{semantic.color.text.inverse}",      "type": "color" },
      "text-disabled":{ "value": "{primitive.color.gray.400}",         "type": "color" }
    },
    "input": {
      "bg":              { "value": "{semantic.color.bg.primary}",      "type": "color" },
      "border-default":  { "value": "{semantic.color.border.default}",  "type": "color" },
      "border-error":    { "value": "{semantic.color.error}",           "type": "color" },
      "text":            { "value": "{semantic.color.text.primary}",    "type": "color" },
      "placeholder":     { "value": "{semantic.color.text.secondary}",  "type": "color" }
    },
    "card": {
      "bg":     { "value": "{semantic.color.bg.primary}",     "type": "color" },
      "border": { "value": "{semantic.color.border.default}", "type": "color" }
    }
  }
}
